[
  {
    "exercise_name": "under-control",
    "started_at": 1755613166.54764,
    "completed_at": 1755613167.183661,
    "comments": [
      "You successfully used git init to initialize this folder as a Git repository!"
    ],
    "status": "Completed"
  },
  {
    "exercise_name": "remote-control",
    "started_at": 1755615769.609083,
    "completed_at": 1755615805.948795,
    "comments": [
      "Great work setting up a public remote repository!"
    ],
    "status": "Completed"
  },
  {
    "exercise_name": "link-me",
    "started_at": 1755616894.057272,
    "completed_at": 1755616894.358596,
    "comments": [
      "Great work with using git remote to add an upstream remote!"
    ],
    "status": "Completed"
  },
  {
    "exercise_name": "push-over",
    "started_at": 1755618520.215654,
    "completed_at": 1755618521.782999,
    "comments": [
      "Great work pushing changes to the remote!"
    ],
    "status": "Completed"
  }
]